pymostactive/__init__.py
pymostactive/base_data_provider.py
pymostactive/most_active.py
pymostactive/tradingview_data_provider.py
pymostactive/web_scraper.py
pymostactive/yahoo_data_provider.py
pymostactive-0.1.1.dist-info/licenses/LICENSE
pymostactive-0.1.1.dist-info/METADATA
pymostactive-0.1.1.dist-info/WHEEL
pymostactive-0.1.1.dist-info/top_level.txt
pymostactive-0.1.1.dist-info/RECORD
