Metadata-Version: 2.4
Name: PyMostActive
Version: 0.1.1
Summary: Retrieve the list of most active stocks from major financial websites.
Author-email: Steven Li <sli@live.ca>
License: MIT
Classifier: Development Status :: 3 - Alpha
Classifier: Intended Audience :: Developers
Classifier: License :: OSI Approved :: MIT License
Classifier: Programming Language :: Python :: 3
Classifier: Programming Language :: Python :: 3.12
Requires-Python: >=3.12
License-File: LICENSE
Requires-Dist: beautifulsoup4
Requires-Dist: requests
Requires-Dist: pandas
Dynamic: license-file
